pythonrun/__init__.py
pythonrun/_version.py
pythonrun/cli.py
pythonrun/main.py
pythonrun/package_mapping.json
pythonrun/stdlib_modules.json
pythonrun/utils.py
pythonrun-1.1.6.dist-info/LICENSE
pythonrun-1.1.6.dist-info/METADATA
pythonrun-1.1.6.dist-info/WHEEL
pythonrun-1.1.6.dist-info/entry_points.txt
pythonrun-1.1.6.dist-info/top_level.txt
pythonrun-1.1.6.dist-info/RECORD
