Metadata-Version: 2.2
Name: pythonrun
Version: 1.1.6
Summary: 自动导入和安装Python模块的工具
Author-email: StevenLi-phoenix <abroad.whinny.3u@icloud.com>
License: MIT
Project-URL: Homepage, https://github.com/StevenLi-phoenix/pythonrun
Project-URL: Bug Tracker, https://github.com/StevenLi-phoenix/pythonrun/issues
Project-URL: Source, https://github.com/StevenLi-phoenix/pythonrun
Keywords: import,package management,dependency,automation
Classifier: Programming Language :: Python :: 3.6
Classifier: Programming Language :: Python :: 3.7
Classifier: Programming Language :: Python :: 3.8
Classifier: Programming Language :: Python :: 3.9
Classifier: Programming Language :: Python :: 3.10
Classifier: Programming Language :: Python :: 3.11
Classifier: Programming Language :: Python :: 3.12
Classifier: Programming Language :: Python :: 3.13
Classifier: License :: OSI Approved :: MIT License
Classifier: Operating System :: OS Independent
Classifier: Development Status :: 5 - Production/Stable
Classifier: Environment :: Console
Classifier: Intended Audience :: Developers
Classifier: Topic :: Software Development :: Libraries :: Python Modules
Requires-Python: >=3.6
License-File: LICENSE
Requires-Dist: requests>=2.25.0
